logninja/__init__.py
logninja/configs.py
logninja/console_interface.py
logninja/contextvars_filter.py
logninja/decorators.py
logninja/format_filter.py
logninja/logger.py
logninja/ninja_console.py
logninja/ninja_formatter.py
logninja/ninja_handler.py
logninja/ninja_json_formatter.py
logninja/ninja_rich_console.py
logninja/options.py
logninja/traceback.py
logninja/utils.py
logninja/asgi/__init__.py
logninja/asgi/middleware.py
logninja-0.1.18.dist-info/LICENSE
logninja-0.1.18.dist-info/METADATA
logninja-0.1.18.dist-info/WHEEL
logninja-0.1.18.dist-info/top_level.txt
logninja-0.1.18.dist-info/RECORD
